LICENSE
MANIFEST.in
README
setup.cfg
setup.py
Flask_FlatPagesCut.egg-info/PKG-INFO
Flask_FlatPagesCut.egg-info/SOURCES.txt
Flask_FlatPagesCut.egg-info/dependency_links.txt
Flask_FlatPagesCut.egg-info/not-zip-safe
Flask_FlatPagesCut.egg-info/requires.txt
Flask_FlatPagesCut.egg-info/top_level.txt
docs/conf.py
docs/index.rst
flask_flatpagescut/__init__.py
flask_flatpagescut/tests.py
flask_flatpagescut/pages/foo.html
flask_flatpagescut/pages/headerid.html
flask_flatpagescut/pages/hello.html
flask_flatpagescut/pages/not_a_page.txt
flask_flatpagescut/pages/foo/bar.html
flask_flatpagescut/pages/foo/42/not_a_page.txt
flask_flatpagescut/pages/foo/lorem/ipsum.html
flask_flatpagescut/pages_shift_jis/hello.html