Metadata-Version: 1.1
Name: Flask-FlatPagesCut
Version: 0.5.1
Summary: Flask-FlatPagesCut is fork Flask-FlatPages (Provides flat static pages to a Flask application)
Home-page: https://github.com/billyfbrain/Flask-FlatPagesCut
Author: Vasily Klyuev
Author-email: billyfbrain@gmail.com
License: BSD
Platform: any
Classifier: Environment :: Web Environment
Classifier: Intended Audience :: Developers
Classifier: License :: OSI Approved :: BSD License
Classifier: Operating System :: OS Independent
Classifier: Programming Language :: Python
Classifier: Topic :: Internet :: WWW/HTTP :: Dynamic Content
Classifier: Topic :: Software Development :: Libraries :: Python Modules
Classifier: Programming Language :: Python :: 2
Classifier: Programming Language :: Python :: 2.5
Classifier: Programming Language :: Python :: 2.6
Classifier: Programming Language :: Python :: 2.7
